sieves/__init__.py
sieves/serialization.py
sieves/data/__init__.py
sieves/data/doc.py
sieves/model_wrappers/__init__.py
sieves/model_wrappers/core.py
sieves/model_wrappers/dspy_.py
sieves/model_wrappers/gliner_.py
sieves/model_wrappers/huggingface_.py
sieves/model_wrappers/langchain_.py
sieves/model_wrappers/model_type.py
sieves/model_wrappers/outlines_.py
sieves/model_wrappers/types.py
sieves/model_wrappers/utils.py
sieves/pipeline/__init__.py
sieves/pipeline/core.py
sieves/tasks/__init__.py
sieves/tasks/core.py
sieves/tasks/types.py
sieves/tasks/utils.py
sieves/tasks/distillation/__init__.py
sieves/tasks/distillation/distillation_import.py
sieves/tasks/distillation/types.py
sieves/tasks/optimization/__init__.py
sieves/tasks/optimization/core.py
sieves/tasks/predictive/__init__.py
sieves/tasks/predictive/bridges.py
sieves/tasks/predictive/core.py
sieves/tasks/predictive/classification/__init__.py
sieves/tasks/predictive/classification/bridges.py
sieves/tasks/predictive/classification/core.py
sieves/tasks/predictive/information_extraction/__init__.py
sieves/tasks/predictive/information_extraction/bridges.py
sieves/tasks/predictive/information_extraction/core.py
sieves/tasks/predictive/ner/__init__.py
sieves/tasks/predictive/ner/bridges.py
sieves/tasks/predictive/ner/core.py
sieves/tasks/predictive/pii_masking/__init__.py
sieves/tasks/predictive/pii_masking/bridges.py
sieves/tasks/predictive/pii_masking/core.py
sieves/tasks/predictive/question_answering/__init__.py
sieves/tasks/predictive/question_answering/bridges.py
sieves/tasks/predictive/question_answering/core.py
sieves/tasks/predictive/sentiment_analysis/__init__.py
sieves/tasks/predictive/sentiment_analysis/bridges.py
sieves/tasks/predictive/sentiment_analysis/core.py
sieves/tasks/predictive/summarization/__init__.py
sieves/tasks/predictive/summarization/bridges.py
sieves/tasks/predictive/summarization/core.py
sieves/tasks/predictive/translation/__init__.py
sieves/tasks/predictive/translation/bridges.py
sieves-0.24.0.dist-info/licenses/LICENSE
sieves-0.24.0.dist-info/METADATA
sieves-0.24.0.dist-info/WHEEL
sieves-0.24.0.dist-info/top_level.txt
sieves-0.24.0.dist-info/RECORD
