Metadata-Version: 2.4
Name: sieves
Version: 0.24.0
Summary: Plug-and-play, zero-shot document processing pipelines.
Home-page: https://github.com/MantisAI/sieves
Author: Matthew Upson, Nick Sorros, Raphael Mitsch, Matthew Maufe, Angelo Di Gianvito
Author-email: hi@mantisnlp.com
License: MIT
Classifier: Development Status :: 3 - Alpha
Classifier: Intended Audience :: Developers
Classifier: Topic :: Software Development :: Libraries
Classifier: License :: OSI Approved :: MIT License
Classifier: Programming Language :: Python :: 3
Classifier: Programming Language :: Python :: 3.12
Requires-Python: ==3.12.*
License-File: LICENSE
Requires-Dist: chonkie<2,>=1
Requires-Dist: datasets<4,>=3
Requires-Dist: jinja2<4,>=3
Requires-Dist: loguru<1,>=0.7
Requires-Dist: pydantic<3,>=2
Requires-Dist: nest-asyncio<2,>=1
Requires-Dist: outlines<2,>=1
Requires-Dist: gliner2<2,>=1.2
Requires-Dist: transformers[torch]<5,>=4
Requires-Dist: dspy-ai<4,>=3
Requires-Dist: dspy<4,>=3
Requires-Dist: accelerate<2,>1.2
Requires-Dist: langchain-core<2,>=1
Requires-Dist: langchain<2,>=1
Requires-Dist: sentencepiece<1
Requires-Dist: json-repair>=0.48.0
Requires-Dist: openai<2,>=1.109.1
Provides-Extra: ingestion
Requires-Dist: docling<3,>=2; extra == "ingestion"
Requires-Dist: marker-pdf[full]<2,>=1.6.1; extra == "ingestion"
Requires-Dist: nltk>=3.9.1; extra == "ingestion"
Provides-Extra: distill
Requires-Dist: setfit<2,>=1.1; extra == "distill"
Requires-Dist: model2vec[train]<0.5,>0.4; extra == "distill"
Provides-Extra: test
Requires-Dist: anthropic<1,>=0.45; extra == "test"
Requires-Dist: langchain-community<0.4,>=0.3.31; extra == "test"
Requires-Dist: langchain-openai<2,>=1; extra == "test"
Requires-Dist: mkdocstrings[python]<1,>=0.27; extra == "test"
Requires-Dist: mkdocs-material<10,>=9.6; extra == "test"
Requires-Dist: pytest<8,>=7; extra == "test"
Requires-Dist: flaky>=3.8.1; extra == "test"
Requires-Dist: pytest-cov>=6; extra == "test"
Requires-Dist: pre-commit<5,>=4; extra == "test"
Requires-Dist: mypy>=1; extra == "test"
Requires-Dist: mypy-extensions>=1; extra == "test"
Requires-Dist: pre-commit<5,>=4; extra == "test"
Dynamic: license-file
